<?xml version="1.0" encoding="UTF-8"?>
<!DOCTYPE QtCreatorToolChains>
<!-- Written by QtCreator 5.0.1, 2021-10-01T00:32:47. -->
<qtcreator>
 <data>
  <variable>ToolChain.0</variable>
  <valuemap type="QVariantMap">
   <value type="QString" key="ProjectExplorer.GccToolChain.OriginalTargetTriple">x86_64-pc-linux-gnu</value>
   <value type="QString" key="ProjectExplorer.GccToolChain.Path">/usr/bin/g++</value>
   <valuelist type="QVariantList" key="ProjectExplorer.GccToolChain.PlatformCodeGenFlags"/>
   <valuelist type="QVariantList" key="ProjectExplorer.GccToolChain.PlatformLinkerFlags"/>
   <valuelist type="QVariantList" key="ProjectExplorer.GccToolChain.SupportedAbis">
    <value type="QString">x86-linux-generic-elf-64bit</value>
   </valuelist>
   <value type="QString" key="ProjectExplorer.GccToolChain.TargetAbi">x86-linux-generic-elf-64bit</value>
   <value type="bool" key="ProjectExplorer.ToolChain.Autodetect">true</value>
   <value type="QString" key="ProjectExplorer.ToolChain.DetectionSource"></value>
   <value type="QString" key="ProjectExplorer.ToolChain.DisplayName">GCC (C++, x86 64bit at /usr/bin/g++)</value>
   <value type="QString" key="ProjectExplorer.ToolChain.Id">ProjectExplorer.ToolChain.Gcc:{b155c39c-0085-4685-998b-83472467bd87}</value>
   <value type="int" key="ProjectExplorer.ToolChain.Language">2</value>
   <value type="QString" key="ProjectExplorer.ToolChain.LanguageV2">Cxx</value>
  </valuemap>
 </data>
 <data>
  <variable>ToolChain.1</variable>
  <valuemap type="QVariantMap">
   <value type="QString" key="ProjectExplorer.GccToolChain.OriginalTargetTriple">x86_64-pc-linux-gnu</value>
   <value type="QString" key="ProjectExplorer.GccToolChain.Path">/usr/bin/gcc</value>
   <valuelist type="QVariantList" key="ProjectExplorer.GccToolChain.PlatformCodeGenFlags"/>
   <valuelist type="QVariantList" key="ProjectExplorer.GccToolChain.PlatformLinkerFlags"/>
   <valuelist type="QVariantList" key="ProjectExplorer.GccToolChain.SupportedAbis">
    <value type="QString">x86-linux-generic-elf-64bit</value>
   </valuelist>
   <value type="QString" key="ProjectExplorer.GccToolChain.TargetAbi">x86-linux-generic-elf-64bit</value>
   <value type="bool" key="ProjectExplorer.ToolChain.Autodetect">true</value>
   <value type="QString" key="ProjectExplorer.ToolChain.DetectionSource"></value>
   <value type="QString" key="ProjectExplorer.ToolChain.DisplayName">GCC (C, x86 64bit at /usr/bin/gcc)</value>
   <value type="QString" key="ProjectExplorer.ToolChain.Id">ProjectExplorer.ToolChain.Gcc:{73b287a2-1bcb-4a80-8208-f136d4d63494}</value>
   <value type="int" key="ProjectExplorer.ToolChain.Language">1</value>
   <value type="QString" key="ProjectExplorer.ToolChain.LanguageV2">C</value>
  </valuemap>
 </data>
 <data>
  <variable>ToolChain.2</variable>
  <valuemap type="QVariantMap">
   <value type="QByteArray" key="ProjectExplorer.ClangToolChain.ParentToolChainId"></value>
   <value type="QString" key="ProjectExplorer.GccToolChain.OriginalTargetTriple">x86_64-pc-linux-gnu</value>
   <value type="QString" key="ProjectExplorer.GccToolChain.Path">/usr/bin/clang++</value>
   <valuelist type="QVariantList" key="ProjectExplorer.GccToolChain.PlatformCodeGenFlags"/>
   <valuelist type="QVariantList" key="ProjectExplorer.GccToolChain.PlatformLinkerFlags"/>
   <valuelist type="QVariantList" key="ProjectExplorer.GccToolChain.SupportedAbis">
    <value type="QString">x86-linux-generic-elf-64bit</value>
   </valuelist>
   <value type="QString" key="ProjectExplorer.GccToolChain.TargetAbi">x86-linux-generic-elf-64bit</value>
   <value type="bool" key="ProjectExplorer.ToolChain.Autodetect">true</value>
   <value type="QString" key="ProjectExplorer.ToolChain.DetectionSource"></value>
   <value type="QString" key="ProjectExplorer.ToolChain.DisplayName">Clang (C++, x86 64bit at /usr/bin/clang++)</value>
   <value type="QString" key="ProjectExplorer.ToolChain.Id">ProjectExplorer.ToolChain.Clang:{6f2e2554-c897-474c-9dd3-48cd1e024319}</value>
   <value type="int" key="ProjectExplorer.ToolChain.Language">2</value>
   <value type="QString" key="ProjectExplorer.ToolChain.LanguageV2">Cxx</value>
  </valuemap>
 </data>
 <data>
  <variable>ToolChain.3</variable>
  <valuemap type="QVariantMap">
   <value type="QByteArray" key="ProjectExplorer.ClangToolChain.ParentToolChainId"></value>
   <value type="QString" key="ProjectExplorer.GccToolChain.OriginalTargetTriple">x86_64-pc-linux-gnu</value>
   <value type="QString" key="ProjectExplorer.GccToolChain.Path">/usr/bin/clang</value>
   <valuelist type="QVariantList" key="ProjectExplorer.GccToolChain.PlatformCodeGenFlags"/>
   <valuelist type="QVariantList" key="ProjectExplorer.GccToolChain.PlatformLinkerFlags"/>
   <valuelist type="QVariantList" key="ProjectExplorer.GccToolChain.SupportedAbis">
    <value type="QString">x86-linux-generic-elf-64bit</value>
   </valuelist>
   <value type="QString" key="ProjectExplorer.GccToolChain.TargetAbi">x86-linux-generic-elf-64bit</value>
   <value type="bool" key="ProjectExplorer.ToolChain.Autodetect">true</value>
   <value type="QString" key="ProjectExplorer.ToolChain.DetectionSource"></value>
   <value type="QString" key="ProjectExplorer.ToolChain.DisplayName">Clang (C, x86 64bit at /usr/bin/clang)</value>
   <value type="QString" key="ProjectExplorer.ToolChain.Id">ProjectExplorer.ToolChain.Clang:{aa5634f2-6622-433f-85f4-29961c7b27c4}</value>
   <value type="int" key="ProjectExplorer.ToolChain.Language">1</value>
   <value type="QString" key="ProjectExplorer.ToolChain.LanguageV2">C</value>
  </valuemap>
 </data>
 <data>
  <variable>ToolChain.Count</variable>
  <value type="int">4</value>
 </data>
 <data>
  <variable>Version</variable>
  <value type="int">1</value>
 </data>
</qtcreator>
